telegram_logging_handler/__init__.py
telegram_logging_handler/handler.py
telegram_logging_handler-0.0.5.dist-info/METADATA
telegram_logging_handler-0.0.5.dist-info/WHEEL
telegram_logging_handler-0.0.5.dist-info/licenses/LICENSE
telegram_logging_handler-0.0.5.dist-info/RECORD
