Metadata-Version: 2.1
Name: telegram_logging_handler
Version: 0.0.5
Summary: Telegram logging handler for python
Project-URL: Homepage, https://github.com/alagakin/telegram_logging_handler
Project-URL: Bug Tracker, https://github.com/alagakin/telegram_logging_handler/issues
Author-email: Alexandr Agakin <agakinalexnadr@gmail.com>
License-File: LICENSE
Classifier: License :: OSI Approved :: MIT License
Classifier: Operating System :: OS Independent
Classifier: Programming Language :: Python :: 3
Requires-Python: >=3.7
Requires-Dist: requests>=2.31
